uuid_lib-0.3.4.dist-info/METADATA
uuid_lib-0.3.4.dist-info/WHEEL
uuid_lib/__init__.pyi
uuid_lib/__init__.py
uuid_lib/py.typed
uuid_lib/_uuid_lib.cpython-312-arm-linux-gnueabihf.so
uuid_lib-0.3.4.dist-info/RECORD
